{"p":"内蒙古自治区","datas":[{"name":"内蒙古大学","code":"4115010126","authorities":"内蒙古自治区","location":"呼和浩特市","level":"本科","tip":""},{"name":"内蒙古科技大学","code":"4115010127","authorities":"内蒙古自治区","location":"包头市","level":"本科","tip":""},{"name":"内蒙古工业大学","code":"4115010128","authorities":"内蒙古自治区","location":"呼和浩特市","level":"本科","tip":""},{"name":"内蒙古农业大学","code":"4115010129","authorities":"内蒙古自治区","location":"呼和浩特市","level":"本科","tip":""},{"name":"内蒙古医科大学","code":"4115010132","authorities":"内蒙古自治区","location":"呼和浩特市","level":"本科","tip":""},{"name":"内蒙古师范大学","code":"4115010135","authorities":"内蒙古自治区","location":"呼和浩特市","level":"本科","tip":""},{"name":"内蒙古民族大学","code":"4115010136","authorities":"内蒙古自治区","location":"通辽市","level":"本科","tip":""},{"name":"赤峰学院","code":"4115010138","authorities":"内蒙古自治区","location":"赤峰市","level":"本科","tip":""},{"name":"内蒙古财经大学","code":"4115010139","authorities":"内蒙古自治区","location":"呼和浩特市","level":"本科","tip":""},{"name":"呼伦贝尔学院","code":"4115010819","authorities":"内蒙古自治区","location":"呼伦贝尔市","level":"本科","tip":""},{"name":"集宁师范学院","code":"4115011427","authorities":"内蒙古自治区","location":"乌兰察布市","level":"本科","tip":""},{"name":"河套学院","code":"4115011631","authorities":"内蒙古自治区","location":"巴彦淖尔市","level":"本科","tip":""},{"name":"呼和浩特民族学院","code":"4115011709","authorities":"内蒙古自治区","location":"呼和浩特市","level":"本科","tip":""},{"name":"内蒙古大学创业学院","code":"4115014199","authorities":"内蒙古自治区教育厅","location":"呼和浩特市","level":"本科","tip":"民办"},{"name":"内蒙古师范大学鸿德学院","code":"4115014205","authorities":"内蒙古自治区教育厅","location":"呼和浩特市","level":"本科","tip":"民办"},{"name":"内蒙古艺术学院","code":"4115014531","authorities":"内蒙古自治区","location":"呼和浩特市","level":"本科","tip":""},{"name":"鄂尔多斯应用技术学院","code":"4115014532","authorities":"内蒙古自治区","location":"鄂尔多斯市","level":"本科","tip":""},{"name":"内蒙古建筑职业技术学院","code":"4115010871","authorities":"内蒙古自治区","location":"呼和浩特市","level":"专科","tip":""},{"name":"内蒙古丰州职业学院","code":"4115011429","authorities":"内蒙古自治区教育厅","location":"呼和浩特市","level":"专科","tip":"民办"},{"name":"包头职业技术学院","code":"4115012057","authorities":"内蒙古自治区","location":"包头市","level":"专科","tip":""},{"name":"兴安职业技术学院","code":"4115012443","authorities":"内蒙古自治区","location":"兴安盟","level":"专科","tip":""},{"name":"呼和浩特职业学院","code":"4115012670","authorities":"内蒙古自治区","location":"呼和浩特市","level":"专科","tip":""},{"name":"包头轻工职业技术学院","code":"4115012671","authorities":"内蒙古自治区","location":"包头市","level":"专科","tip":""},{"name":"内蒙古电子信息职业技术学院","code":"4115012673","authorities":"内蒙古自治区","location":"呼和浩特市","level":"专科","tip":""},{"name":"内蒙古机电职业技术学院","code":"4115012674","authorities":"内蒙古自治区","location":"呼和浩特市","level":"专科","tip":""},{"name":"内蒙古化工职业学院","code":"4115012675","authorities":"内蒙古自治区","location":"呼和浩特市","level":"专科","tip":""},{"name":"内蒙古商贸职业学院","code":"4115012676","authorities":"内蒙古自治区","location":"呼和浩特市","level":"专科","tip":""},{"name":"锡林郭勒职业学院","code":"4115012677","authorities":"内蒙古自治区","location":"锡林郭勒盟","level":"专科","tip":""},{"name":"内蒙古警察职业学院","code":"4115012797","authorities":"内蒙古自治区","location":"呼和浩特市","level":"专科","tip":""},{"name":"内蒙古体育职业学院","code":"4115012894","authorities":"内蒙古自治区","location":"呼和浩特市","level":"专科","tip":""},{"name":"乌兰察布职业学院","code":"4115013699","authorities":"内蒙古自治区","location":"乌兰察布市","level":"专科","tip":""},{"name":"通辽职业学院","code":"4115013740","authorities":"内蒙古自治区","location":"通辽市","level":"专科","tip":""},{"name":"科尔沁艺术职业学院","code":"4115013741","authorities":"内蒙古自治区","location":"通辽市","level":"专科","tip":""},{"name":"内蒙古交通职业技术学院","code":"4115013824","authorities":"内蒙古自治区","location":"赤峰市","level":"专科","tip":""},{"name":"包头钢铁职业技术学院","code":"4115013864","authorities":"内蒙古自治区","location":"包头市","level":"专科","tip":""},{"name":"乌海职业技术学院","code":"4115013915","authorities":"内蒙古自治区","location":"乌海市","level":"专科","tip":""},{"name":"内蒙古科技职业学院","code":"4115014048","authorities":"内蒙古自治区教育厅","location":"呼和浩特市","level":"专科","tip":"民办"},{"name":"内蒙古北方职业技术学院","code":"4115014049","authorities":"内蒙古自治区教育厅","location":"呼和浩特市","level":"专科","tip":"民办"},{"name":"赤峰职业技术学院","code":"4115014050","authorities":"内蒙古自治区教育厅","location":"赤峰市","level":"专科","tip":"民办"},{"name":"内蒙古经贸外语职业学院","code":"4115014051","authorities":"内蒙古自治区教育厅","location":"呼和浩特市","level":"专科","tip":"民办"},{"name":"包头铁道职业技术学院","code":"4115014187","authorities":"内蒙古自治区","location":"包头市","level":"专科","tip":""},{"name":"乌兰察布医学高等专科学校","code":"4115014219","authorities":"内蒙古自治区","location":"乌兰察布市","level":"专科","tip":""},{"name":"鄂尔多斯职业学院","code":"4115014248","authorities":"内蒙古自治区","location":"鄂尔多斯市","level":"专科","tip":""},{"name":"内蒙古工业职业学院","code":"4115014282","authorities":"内蒙古自治区教育厅","location":"呼和浩特市","level":"专科","tip":"民办"},{"name":"呼伦贝尔职业技术学院","code":"4115014283","authorities":"内蒙古自治区","location":"呼伦贝尔市","level":"专科","tip":""},{"name":"满洲里俄语职业学院","code":"4115014285","authorities":"内蒙古自治区","location":"呼伦贝尔市","level":"专科","tip":""},{"name":"内蒙古能源职业学院","code":"4115014337","authorities":"内蒙古自治区教育厅","location":"呼和浩特市","level":"专科","tip":"民办"},{"name":"赤峰工业职业技术学院","code":"4115014338","authorities":"内蒙古自治区","location":"赤峰市","level":"专科","tip":""},{"name":"阿拉善职业技术学院","code":"4115014339","authorities":"内蒙古自治区","location":"阿拉善盟","level":"专科","tip":""},{"name":"内蒙古美术职业学院","code":"4115014387","authorities":"内蒙古自治区教育厅","location":"巴彦淖尔市","level":"专科","tip":"民办"},{"name":"内蒙古民族幼儿师范高等专科学校","code":"4115014463","authorities":"内蒙古自治区","location":"鄂尔多斯市","level":"专科","tip":""},{"name":"鄂尔多斯生态环境职业学院","code":"4115014501","authorities":"内蒙古自治区","location":"鄂尔多斯市","level":"专科","tip":""},{"name":"扎兰屯职业学院","code":"4115014539","authorities":"内蒙古自治区","location":"呼伦贝尔市","level":"专科","tip":""}]}