{"p":"安徽省","datas":[{"name":"安徽大学","code":"4134010357","authorities":"安徽省","location":"合肥市","level":"本科","tip":""},{"name":"中国科学技术大学","code":"4134010358","authorities":"中国科学院","location":"合肥市","level":"本科","tip":""},{"name":"合肥工业大学","code":"4134010359","authorities":"教育部","location":"合肥市","level":"本科","tip":""},{"name":"安徽工业大学","code":"4134010360","authorities":"安徽省","location":"马鞍山市","level":"本科","tip":""},{"name":"安徽理工大学","code":"4134010361","authorities":"安徽省","location":"淮南市","level":"本科","tip":""},{"name":"安徽工程大学","code":"4134010363","authorities":"安徽省","location":"芜湖市","level":"本科","tip":""},{"name":"安徽农业大学","code":"4134010364","authorities":"安徽省","location":"合肥市","level":"本科","tip":""},{"name":"安徽医科大学","code":"4134010366","authorities":"安徽省","location":"合肥市","level":"本科","tip":""},{"name":"蚌埠医学院","code":"4134010367","authorities":"安徽省","location":"蚌埠市","level":"本科","tip":""},{"name":"皖南医学院","code":"4134010368","authorities":"安徽省","location":"芜湖市","level":"本科","tip":""},{"name":"安徽中医药大学","code":"4134010369","authorities":"安徽省","location":"合肥市","level":"本科","tip":""},{"name":"安徽师范大学","code":"4134010370","authorities":"安徽省","location":"芜湖市","level":"本科","tip":""},{"name":"阜阳师范大学","code":"4134010371","authorities":"安徽省","location":"阜阳市","level":"本科","tip":""},{"name":"安庆师范大学","code":"4134010372","authorities":"安徽省","location":"安庆市","level":"本科","tip":""},{"name":"淮北师范大学","code":"4134010373","authorities":"安徽省","location":"淮北市","level":"本科","tip":""},{"name":"黄山学院","code":"4134010375","authorities":"安徽省","location":"黄山市","level":"本科","tip":""},{"name":"皖西学院","code":"4134010376","authorities":"安徽省","location":"六安市","level":"本科","tip":""},{"name":"滁州学院","code":"4134010377","authorities":"安徽省","location":"滁州市","level":"本科","tip":""},{"name":"安徽财经大学","code":"4134010378","authorities":"安徽省","location":"蚌埠市","level":"本科","tip":""},{"name":"宿州学院","code":"4134010379","authorities":"安徽省","location":"宿州市","level":"本科","tip":""},{"name":"巢湖学院","code":"4134010380","authorities":"安徽省","location":"合肥市","level":"本科","tip":""},{"name":"淮南师范学院","code":"4134010381","authorities":"安徽省","location":"淮南市","level":"本科","tip":""},{"name":"铜陵学院","code":"4134010383","authorities":"安徽省","location":"铜陵市","level":"本科","tip":""},{"name":"安徽建筑大学","code":"4134010878","authorities":"安徽省","location":"合肥市","level":"本科","tip":""},{"name":"安徽科技学院","code":"4134010879","authorities":"安徽省","location":"滁州市","level":"本科","tip":""},{"name":"安徽三联学院","code":"4134010959","authorities":"安徽省教育厅","location":"合肥市","level":"本科","tip":"民办"},{"name":"合肥学院","code":"4134011059","authorities":"安徽省","location":"合肥市","level":"本科","tip":""},{"name":"蚌埠学院","code":"4134011305","authorities":"安徽省","location":"蚌埠市","level":"本科","tip":""},{"name":"池州学院","code":"4134011306","authorities":"安徽省","location":"池州市","level":"本科","tip":""},{"name":"安徽新华学院","code":"4134012216","authorities":"安徽省教育厅","location":"合肥市","level":"本科","tip":"民办"},{"name":"安徽文达信息工程学院","code":"4134012810","authorities":"安徽省教育厅","location":"合肥市","level":"本科","tip":"民办"},{"name":"亳州学院","code":"4134012926","authorities":"安徽省","location":"亳州市","level":"本科","tip":""},{"name":"安徽外国语学院","code":"4134013065","authorities":"安徽省教育厅","location":"合肥市","level":"本科","tip":"民办"},{"name":"安徽财经大学商学院","code":"4134013611","authorities":"安徽省教育厅","location":"蚌埠市","level":"本科","tip":"民办"},{"name":"安徽大学江淮学院","code":"4134013612","authorities":"安徽省教育厅","location":"合肥市","level":"本科","tip":"民办"},{"name":"安徽信息工程学院","code":"4134013613","authorities":"安徽省教育厅","location":"芜湖市","level":"本科","tip":"民办"},{"name":"安徽工业大学工商学院","code":"4134013614","authorities":"安徽省教育厅","location":"马鞍山市","level":"本科","tip":"民办"},{"name":"安徽建筑大学城市建设学院","code":"4134013615","authorities":"安徽省教育厅","location":"合肥市","level":"本科","tip":"民办"},{"name":"安徽农业大学经济技术学院","code":"4134013616","authorities":"安徽省教育厅","location":"合肥市","level":"本科","tip":"民办"},{"name":"安徽师范大学皖江学院","code":"4134013617","authorities":"安徽省教育厅","location":"芜湖市","level":"本科","tip":"民办"},{"name":"安徽医科大学临床医学院","code":"4134013618","authorities":"安徽省教育厅","location":"合肥市","level":"本科","tip":"民办"},{"name":"阜阳师范学院信息工程学院","code":"4134013619","authorities":"安徽省教育厅","location":"阜阳市","level":"本科","tip":"民办"},{"name":"淮北师范大学信息学院","code":"4134013620","authorities":"安徽省教育厅","location":"淮北市","level":"本科","tip":"民办"},{"name":"合肥师范学院","code":"4134014098","authorities":"安徽省","location":"合肥市","level":"本科","tip":""},{"name":"河海大学文天学院","code":"4134014203","authorities":"安徽省教育厅","location":"马鞍山市","level":"本科","tip":"民办"},{"name":"安徽职业技术学院","code":"4134010869","authorities":"安徽省","location":"合肥市","level":"专科","tip":""},{"name":"淮北职业技术学院","code":"4134010963","authorities":"安徽省","location":"淮北市","level":"专科","tip":""},{"name":"芜湖职业技术学院","code":"4134011061","authorities":"安徽省","location":"芜湖市","level":"专科","tip":""},{"name":"淮南联合大学","code":"4134011308","authorities":"安徽省","location":"淮南市","level":"专科","tip":""},{"name":"安徽商贸职业技术学院","code":"4134012072","authorities":"安徽省","location":"芜湖市","level":"专科","tip":""},{"name":"安徽水利水电职业技术学院","code":"4134012073","authorities":"安徽省","location":"合肥市","level":"专科","tip":""},{"name":"阜阳职业技术学院","code":"4134012074","authorities":"安徽省","location":"阜阳市","level":"专科","tip":""},{"name":"铜陵职业技术学院","code":"4134012217","authorities":"安徽省","location":"铜陵市","level":"专科","tip":""},{"name":"民办万博科技职业学院","code":"4134012218","authorities":"安徽省教育厅","location":"合肥市","level":"专科","tip":"民办"},{"name":"安徽警官职业学院","code":"4134012219","authorities":"安徽省","location":"合肥市","level":"专科","tip":""},{"name":"淮南职业技术学院","code":"4134012220","authorities":"安徽省","location":"淮南市","level":"专科","tip":""},{"name":"安徽工业经济职业技术学院","code":"4134012334","authorities":"安徽省","location":"合肥市","level":"专科","tip":""},{"name":"合肥通用职业技术学院","code":"4134012410","authorities":"安徽省","location":"合肥市","level":"专科","tip":""},{"name":"安徽工贸职业技术学院","code":"4134012811","authorities":"安徽省","location":"淮南市","level":"专科","tip":""},{"name":"宿州职业技术学院","code":"4134012812","authorities":"安徽省","location":"宿州市","level":"专科","tip":""},{"name":"六安职业技术学院","code":"4134012813","authorities":"安徽省","location":"六安市","level":"专科","tip":""},{"name":"安徽电子信息职业技术学院","code":"4134012814","authorities":"安徽省","location":"蚌埠市","level":"专科","tip":""},{"name":"民办合肥经济技术职业学院","code":"4134012815","authorities":"安徽省教育厅","location":"合肥市","level":"专科","tip":"民办"},{"name":"安徽交通职业技术学院","code":"4134012816","authorities":"安徽省","location":"合肥市","level":"专科","tip":""},{"name":"安徽体育运动职业技术学院","code":"4134012817","authorities":"安徽省","location":"合肥市","level":"专科","tip":""},{"name":"安徽中医药高等专科学校","code":"4134012924","authorities":"安徽省","location":"芜湖市","level":"专科","tip":""},{"name":"安徽医学高等专科学校","code":"4134012925","authorities":"安徽省","location":"合肥市","level":"专科","tip":""},{"name":"合肥职业技术学院","code":"4134013058","authorities":"安徽省","location":"合肥市","level":"专科","tip":""},{"name":"滁州职业技术学院","code":"4134013059","authorities":"安徽省","location":"滁州市","level":"专科","tip":""},{"name":"池州职业技术学院","code":"4134013060","authorities":"安徽省","location":"池州市","level":"专科","tip":""},{"name":"宣城职业技术学院","code":"4134013061","authorities":"安徽省","location":"宣城市","level":"专科","tip":""},{"name":"安徽广播影视职业技术学院","code":"4134013062","authorities":"安徽省","location":"合肥市","level":"专科","tip":""},{"name":"民办合肥滨湖职业技术学院","code":"4134013064","authorities":"安徽省教育厅","location":"合肥市","level":"专科","tip":"民办"},{"name":"安徽电气工程职业技术学院","code":"4134013336","authorities":"安徽省","location":"合肥市","level":"专科","tip":""},{"name":"安徽冶金科技职业学院","code":"4134013337","authorities":"安徽省","location":"马鞍山市","level":"专科","tip":""},{"name":"安徽城市管理职业学院","code":"4134013338","authorities":"安徽省","location":"合肥市","level":"专科","tip":""},{"name":"安徽机电职业技术学院","code":"4134013339","authorities":"安徽省","location":"芜湖市","level":"专科","tip":""},{"name":"安徽工商职业学院","code":"4134013340","authorities":"安徽省","location":"合肥市","level":"专科","tip":""},{"name":"安徽中澳科技职业学院","code":"4134013341","authorities":"安徽省","location":"合肥市","level":"专科","tip":""},{"name":"阜阳科技职业学院","code":"4134013342","authorities":"安徽省教育厅","location":"阜阳市","level":"专科","tip":"民办"},{"name":"亳州职业技术学院","code":"4134013343","authorities":"安徽省","location":"亳州市","level":"专科","tip":""},{"name":"安徽国防科技职业学院","code":"4134013344","authorities":"安徽省","location":"六安市","level":"专科","tip":""},{"name":"安庆职业技术学院","code":"4134013345","authorities":"安徽省","location":"安庆市","level":"专科","tip":""},{"name":"安徽艺术职业学院","code":"4134013346","authorities":"安徽省","location":"合肥市","level":"专科","tip":""},{"name":"马鞍山师范高等专科学校","code":"4134013760","authorities":"安徽省","location":"马鞍山市","level":"专科","tip":""},{"name":"安徽财贸职业学院","code":"4134013845","authorities":"安徽省","location":"合肥市","level":"专科","tip":""},{"name":"安徽国际商务职业学院","code":"4134013846","authorities":"安徽省","location":"合肥市","level":"专科","tip":""},{"name":"安徽公安职业学院","code":"4134013847","authorities":"安徽省","location":"合肥市","level":"专科","tip":""},{"name":"安徽林业职业技术学院","code":"4134013848","authorities":"安徽省","location":"合肥市","level":"专科","tip":""},{"name":"安徽审计职业学院","code":"4134013849","authorities":"安徽省","location":"合肥市","level":"专科","tip":""},{"name":"安徽新闻出版职业技术学院","code":"4134013850","authorities":"安徽省","location":"合肥市","level":"专科","tip":""},{"name":"安徽邮电职业技术学院","code":"4134013851","authorities":"安徽省","location":"合肥市","level":"专科","tip":""},{"name":"安徽工业职业技术学院","code":"4134013852","authorities":"安徽省","location":"铜陵市","level":"专科","tip":""},{"name":"民办合肥财经职业学院","code":"4134014058","authorities":"安徽省教育厅","location":"合肥市","level":"专科","tip":"民办"},{"name":"安庆医药高等专科学校","code":"4134014096","authorities":"安徽省","location":"安庆市","level":"专科","tip":""},{"name":"安徽涉外经济职业学院","code":"4134014132","authorities":"安徽省教育厅","location":"合肥市","level":"专科","tip":"民办"},{"name":"安徽绿海商务职业学院","code":"4134014133","authorities":"安徽省教育厅","location":"合肥市","level":"专科","tip":"民办"},{"name":"合肥共达职业技术学院","code":"4134014135","authorities":"安徽省教育厅","location":"合肥市","level":"专科","tip":"民办"},{"name":"蚌埠经济技术职业学院","code":"4134014137","authorities":"安徽省教育厅","location":"蚌埠市","level":"专科","tip":"民办"},{"name":"民办安徽旅游职业学院","code":"4134014165","authorities":"安徽省教育厅","location":"阜阳市","level":"专科","tip":"民办"},{"name":"徽商职业学院","code":"4134014191","authorities":"安徽省","location":"合肥市","level":"专科","tip":""},{"name":"马鞍山职业技术学院","code":"4134014192","authorities":"安徽省","location":"马鞍山市","level":"专科","tip":""},{"name":"安徽现代信息工程职业学院","code":"4134014210","authorities":"安徽省教育厅","location":"六安市","level":"专科","tip":"民办"},{"name":"安徽矿业职业技术学院","code":"4134014229","authorities":"安徽省教育厅","location":"淮北市","level":"专科","tip":"民办"},{"name":"合肥信息技术职业学院","code":"4134014230","authorities":"安徽省教育厅","location":"合肥市","level":"专科","tip":"民办"},{"name":"桐城师范高等专科学校","code":"4134014273","authorities":"安徽省","location":"安庆市","level":"专科","tip":""},{"name":"黄山职业技术学院","code":"4134014296","authorities":"安徽省","location":"黄山市","level":"专科","tip":""},{"name":"滁州城市职业学院","code":"4134014297","authorities":"安徽省","location":"滁州市","level":"专科","tip":""},{"name":"安徽汽车职业技术学院","code":"4134014298","authorities":"安徽省","location":"合肥市","level":"专科","tip":""},{"name":"皖西卫生职业学院","code":"4134014299","authorities":"安徽省","location":"六安市","level":"专科","tip":""},{"name":"合肥幼儿师范高等专科学校","code":"4134014330","authorities":"安徽省","location":"合肥市","level":"专科","tip":""},{"name":"安徽长江职业学院","code":"4134014341","authorities":"安徽省教育厅","location":"合肥市","level":"专科","tip":"民办"},{"name":"安徽扬子职业技术学院","code":"4134014342","authorities":"安徽省教育厅","location":"芜湖市","level":"专科","tip":"民办"},{"name":"安徽黄梅戏艺术职业学院","code":"4134014378","authorities":"安徽省","location":"安庆市","level":"专科","tip":""},{"name":"安徽粮食工程职业学院","code":"4134014418","authorities":"安徽省","location":"合肥市","level":"专科","tip":""},{"name":"安徽卫生健康职业学院","code":"4134014419","authorities":"安徽省","location":"池州市","level":"专科","tip":""},{"name":"合肥科技职业学院","code":"4134014420","authorities":"安徽省教育厅","location":"合肥市","level":"专科","tip":"民办"},{"name":"皖北卫生职业学院","code":"4134014502","authorities":"安徽省","location":"宿州市","level":"专科","tip":""},{"name":"阜阳幼儿师范高等专科学校","code":"4134014536","authorities":"安徽省","location":"阜阳市","level":"专科","tip":""}]}