{"logo":"https://ss0.bdstatic.com/9bA1vGfa2gU2pMbfm9GUKT-w/timg?wisealaddin&size=8&quality=60&sec=1534499416&di=22adf6501107d1036ebf8d646baec0fd&src=http%3A%2F%2Fh.hiphotos.baidu.com%2Fxiaodu%2Fpic%2Fitem%2F38dbb6fd5266d0163e0835049f2bd40735fa358c.jpg","summary":"东南大学成贤学院(Southeast University Chengxian College)，简称东大成贤，始创于1998年，2003年经教育部批准更用现名。坐落于南京市，是经国家教育部批准成立的全日制普通本科高校，由“985”“211”重点建设高校——东南大学在培养高水平应用型人才、服务国家和社会经济发展层面，用全新的办学理念和运行模式举办的独立学院。截至2017年6月，东南大学成贤学院占地面积1200亩，坐落于东南大学浦口校区；设有7个学院(部)，拥有30个本科专业；有全日制在校生10000余人。是一所以工科为主的应用型本科高校。学校秉承东南大学百年办学优良传统，紧密依托东南大学雄厚的学科资源和优质的教学资源，以“人才需求大、国内有影响、就业前景好、支撑力量强”为专业设置原则，所设专业以社会需求旺盛的工科专业为主。2007年教育主管部门批准我院17个专业列入江苏省本二批次招生，2014年全部专业(含方向)列入本二批次招生，是全国列入本二批次招生专业和人数最多的独立学院。","tags":["综合类","本科","民办"],"attrs":{"创建时间":"1998","所在地区":"南京市浦口区东大路6号","院校隶属":"江苏省教育厅"},"imgs":["https://ss0.bdstatic.com/9bA1vGfa2gU2pMbfm9GUKT-w/timg?wisealaddin&size=f300_300&quality=60&sec=1534499416&di=19e6c04a77eae9fd7b0e7e3926472da4&src=http%3A%2F%2Ft12.baidu.com%2Fit%2Fu%3D3683870981%2C830071305%26fm%3D179%26w%3D300%26h%3D300%26img.JPEG","https://ss0.bdstatic.com/9bA1vGfa2gU2pMbfm9GUKT-w/timg?wisealaddin&size=f300_300&quality=60&sec=1534499416&di=c9b7618cd564c68a867b862f8757db02&src=http%3A%2F%2Ft11.baidu.com%2Fit%2Fu%3D2868193426%2C2761062921%26fm%3D179%26w%3D300%26h%3D300%26img.JPEG","https://ss0.bdstatic.com/9bA1vGfa2gU2pMbfm9GUKT-w/timg?wisealaddin&size=f300_300&quality=60&sec=1534499416&di=b26356fbac91a949fb058f23e3584107&src=http%3A%2F%2Ft12.baidu.com%2Fit%2Fu%3D3671594282%2C734977220%26fm%3D179%26w%3D300%26h%3D300%26img.JPEG","https://ss0.bdstatic.com/9bA1vGfa2gU2pMbfm9GUKT-w/timg?wisealaddin&size=f300_300&quality=60&sec=1534499416&di=8ae1dec0206dcb258486c4ed9fed8587&src=http%3A%2F%2Ft12.baidu.com%2Fit%2Fu%3D3846800816%2C1074582867%26fm%3D179%26w%3D300%26h%3D300%26img.JPEG","https://ss0.bdstatic.com/9bA1vGfa2gU2pMbfm9GUKT-w/timg?wisealaddin&size=f300_300&quality=60&sec=1534499416&di=fdbf6b79cdf26184891c32c90eb1ad5c&src=http%3A%2F%2Ft10.baidu.com%2Fit%2Fu%3D4021122033%2C3232957673%26fm%3D179%26app%3D42%26f%3DJPEG%3Fw%3D300%26h%3D300","https://ss0.bdstatic.com/9bA1vGfa2gU2pMbfm9GUKT-w/timg?wisealaddin&size=f300_300&quality=60&sec=1534499416&di=a51c97f73675b5dfe1523bfd4a2c6328&src=http%3A%2F%2Ft10.baidu.com%2Fit%2Fu%3D2762390223%2C4150126222%26fm%3D179%26app%3D42%26f%3DJPEG%3Fw%3D300%26h%3D300"]}