{"logo":"https://dxzd-imgs.oss-cn-shanghai.aliyuncs.com/8FCD9AC1-FEF3-4243-A701-DC78498ED0B6.jpeg","summary":"中央戏剧学院(The Central Academy of Drama)，由中华人民共和国教育部直属，是中国高等戏剧教育联盟总部、亚洲戏剧教育研究中心总部和世界戏剧院校联盟秘书处所在地，世界戏剧院校联盟国际大学生戏剧节活动基地，国家首批“双一流”学科建设高校，中国政府奖学金来华留学生接收院校。中央戏剧学院拥有联合国教科文组织戏剧教育席位，是新中国第一所戏剧教育高等学校。中央戏剧学院的历史可以溯源至1938年4月10日成立的延安鲁迅艺术学院；1949年12月，中央戏剧学院正式开办；1950年4月2日，中央戏剧学院成立大会召开，毛泽东主席亲笔题写校名。据2015年12月学校官网信息显示，中央戏剧学院有2个校区(东城校区、昌平校区)，总占地面积约23万平方米，建筑面积约18万平方米；下辖10个教学系，开办7个本科专业；在校学生2199人(截至2014年9月)，专任教师244人(截至2014年8月)。","tags":["艺术类","双一流","本科","公办"],"attrs":{"创建时间":"1950","地址":"北京市东城区东棉花胡同39号","院校隶属":"中华人民共和国教育部","重点学科数":"1","院士数":"37","博士点":"2","硕士点":"3"},"imgs":["https://dxzd-imgs.oss-cn-shanghai.aliyuncs.com/DB175DB1-8525-4779-AAFF-8729652F05BF.jpeg","https://dxzd-imgs.oss-cn-shanghai.aliyuncs.com/2F8B128A-4812-4D98-8201-09D0BF2AB9A2.jpeg","https://dxzd-imgs.oss-cn-shanghai.aliyuncs.com/CF47D85A-72FE-4CC4-96B0-E2A98BD3EB29.jpeg","https://dxzd-imgs.oss-cn-shanghai.aliyuncs.com/3C9E87D6-7B4B-49AE-A99C-9D1F5CF35C23.jpeg","https://dxzd-imgs.oss-cn-shanghai.aliyuncs.com/6EF39AB3-AEA1-4275-BC98-3739881863C3.jpeg","https://dxzd-imgs.oss-cn-shanghai.aliyuncs.com/540244A4-7872-4C0F-BCAB-3AA79E07F0EC.jpeg","https://dxzd-imgs.oss-cn-shanghai.aliyuncs.com/F5B60A44-54B1-4BA5-A898-7839AE0A87C8.jpeg"]}