{"logo":"https://ss0.bdstatic.com/9bA1vGfa2gU2pMbfm9GUKT-w/timg?wisealaddin&size=8&quality=60&sec=1534504444&di=c0777835fc42ccdad7f779795d9f8624&src=http%3A%2F%2Fhiphotos.baidu.com%2Fdoc%2Fpic%2Fitem%2F5ab5c9ea15ce36d39cd0b03c30f33a87e850b1e1.jpg","summary":"云南工程职业学院是于2005年经云南省人民政府批准、国家教育部备案、具有独立颁发国家承认学历文凭资格的全日制高等院校，是云南省内同批次院校中最早一所以工科为主的综合类院校，填补了云南省民办高职院校的定位空白点。","tags":["综合类","专科","民办"],"attrs":{"所在地区":"云南省昆明市安宁温泉"},"imgs":["https://ss0.bdstatic.com/9bA1vGfa2gU2pMbfm9GUKT-w/timg?wisealaddin&size=f300_300&quality=60&sec=1534504444&di=ff44ad8907c51c2143cd7deacd469be7&src=http%3A%2F%2Ft12.baidu.com%2Fit%2Fu%3D3803459015%2C1116425109%26fm%3D179%26w%3D300%26h%3D300%26img.JPEG","https://ss0.bdstatic.com/9bA1vGfa2gU2pMbfm9GUKT-w/timg?wisealaddin&size=f300_300&quality=60&sec=1534504444&di=39340febc266f50d3077f63dbbb901d6&src=http%3A%2F%2Ft12.baidu.com%2Fit%2Fu%3D2632807235%2C2570293263%26fm%3D179%26w%3D300%26h%3D300%26img.JPEG","https://ss0.bdstatic.com/9bA1vGfa2gU2pMbfm9GUKT-w/timg?wisealaddin&size=f300_300&quality=60&sec=1534504444&di=d657fe74ee071aae6e54a47fc6e2e243&src=http%3A%2F%2Ft12.baidu.com%2Fit%2Fu%3D3575634155%2C3905061342%26fm%3D179%26w%3D300%26h%3D300%26img.JPEG","https://ss0.bdstatic.com/9bA1vGfa2gU2pMbfm9GUKT-w/timg?wisealaddin&size=f300_300&quality=60&sec=1534504444&di=e2b333bc68e3830e573f923e287123a4&src=http%3A%2F%2Ft10.baidu.com%2Fit%2Fu%3D3610664673%2C769210777%26fm%3D179%26w%3D300%26h%3D300%26img.JPEG","https://ss0.bdstatic.com/9bA1vGfa2gU2pMbfm9GUKT-w/timg?wisealaddin&size=f300_300&quality=60&sec=1534504444&di=74a26493b4a9f7e970718ff5c351fe5b&src=http%3A%2F%2Ft12.baidu.com%2Fit%2Fu%3D2523265214%2C656906398%26fm%3D179%26app%3D42%26f%3DJPEG%3Fw%3D300%26h%3D300","https://ss0.bdstatic.com/9bA1vGfa2gU2pMbfm9GUKT-w/timg?wisealaddin&size=f300_300&quality=60&sec=1534504444&di=27399e4b7decec95dde33fa1f14744b2&src=http%3A%2F%2Ft12.baidu.com%2Fit%2Fu%3D2724729149%2C2061040396%26fm%3D179%26app%3D42%26f%3DJPEG%3Fw%3D300%26h%3D300"]}