{"logo":"https://ss0.bdstatic.com/9bA1vGfa2gU2pMbfm9GUKT-w/timg?wisealaddin&size=8&quality=60&sec=1534499601&di=8ed9307527cdf212cf4165f5e50b06b4&src=http%3A%2F%2Fhiphotos.baidu.com%2Fdoc%2Fpic%2Fitem%2Fbd3eb13533fa828b3ce5a453f71f4134960a5abf.jpg","summary":"亳州学院(Bozhou University)，简称亳院，位于安徽省亳州市，是经国家教育部批准成立的全日制普通本科高等学校。清朝宣统元年(1909年)二月，张廷扬在慈氏寺创办蒙城师资讲习所；1952年，建成蒙城师范学校；2002年，升格为亳州师范高等专科学校；2016年3月22日，经教育部批准升格为普通本科亳州学院。据2016年8月学校官网显示，学校占地面积925亩，建筑面积25.3万平方米，教学仪器设备总值7000余万元，固定资产6亿元，馆藏图书63万册；开设10个院系，开办15个本科专业、34个专科专业；共有教职工400人，专任教师385人，副教授以上职称133人，教授35人，全日制在校生6200人。","tags":["综合类","本科","公办"],"attrs":{"所在地区":"安徽省亳州市经济开发区汤王大道2266号"},"imgs":["https://ss0.bdstatic.com/9bA1vGfa2gU2pMbfm9GUKT-w/timg?wisealaddin&size=f300_300&quality=60&sec=1534499601&di=5fe39b72478845fa7d3b33553da684f0&src=http%3A%2F%2Ft10.baidu.com%2Fit%2Fu%3D3711418248%2C753096555%26fm%3D179%26w%3D300%26h%3D300%26img.JPEG","https://ss0.bdstatic.com/9bA1vGfa2gU2pMbfm9GUKT-w/timg?wisealaddin&size=f300_300&quality=60&sec=1534499601&di=4d4d1d68981859c6e48c60fd3889ae35&src=http%3A%2F%2Ft12.baidu.com%2Fit%2Fu%3D3401839016%2C3971388181%26fm%3D179%26w%3D300%26h%3D300%26img.JPEG","https://ss0.bdstatic.com/9bA1vGfa2gU2pMbfm9GUKT-w/timg?wisealaddin&size=f300_300&quality=60&sec=1534499601&di=842974e0a6311f7ef07ef6f5fe8b681c&src=http%3A%2F%2Ft11.baidu.com%2Fit%2Fu%3D3590566216%2C767444653%26fm%3D179%26w%3D300%26h%3D300%26img.JPEG","https://ss0.bdstatic.com/9bA1vGfa2gU2pMbfm9GUKT-w/timg?wisealaddin&size=f300_300&quality=60&sec=1534499601&di=b87fc0c4dc4d8af495c9dae589044cd1&src=http%3A%2F%2Ft11.baidu.com%2Fit%2Fu%3D3516959548%2C4014364699%26fm%3D179%26w%3D300%26h%3D300%26img.JPEG","https://ss0.bdstatic.com/9bA1vGfa2gU2pMbfm9GUKT-w/timg?wisealaddin&size=f300_300&quality=60&sec=1534499601&di=8095f95adabcbc9891175a05364f2993&src=http%3A%2F%2Ft11.baidu.com%2Fit%2Fu%3D3680223865%2C816677081%26fm%3D179%26w%3D300%26h%3D300%26img.JPEG","https://ss0.bdstatic.com/9bA1vGfa2gU2pMbfm9GUKT-w/timg?wisealaddin&size=f300_300&quality=60&sec=1534499601&di=7494d7c96a9c20883ac37c648d34ac85&src=http%3A%2F%2Ft12.baidu.com%2Fit%2Fu%3D3778445876%2C955742421%26fm%3D179%26w%3D300%26h%3D300%26img.JPEG"]}