{"logo":"https://ss0.bdstatic.com/9bA1vGfa2gU2pMbfm9GUKT-w/timg?wisealaddin&size=8&quality=60&sec=1534504635&di=7f5dfa70b61dda878ccfb9320cf5c9a0&src=http%3A%2F%2Fa.hiphotos.baidu.com%2Fxiaodu%2Fpic%2Fitem%2F810a19d8bc3eb1353b521c97ae1ea8d3fd1f4400.jpg","summary":"兰州财经大学长青学院(Changqing School of Lanzhou University of Finance and Economics)成立于2001年，位于甘肃省兰州市城关区。2004年2月被教育部确认为甘肃省首批独立学院，属本科层次普通高等院校。学院面向全国招生，招生纳入国家普通高校统招计划。2015年6月更名为兰州财经大学长青学院。经过十五年坚持不懈的努力，已经发展成为一所万人规模，在西部地区有重要地位、全国有一定影响的财经类公立独立学院。学院紧密围绕国家战略和地方战略，切实落实就业工作，近几年毕业生总体就业率连年稳定在80%以上。截止2016年6月，学院有雁儿湾、鱼池口两校区，占地面积15.4万平方米，校舍建筑面积14.8万平方米。学院设会计学系、工商管理系、财政金融系、经济贸易系、计算机科学系、艺术系、外语系等7个系和体育教学部，下设29个本科专业，涵盖了经、管、文、工、艺5大门类，包括金融学、会计学、国际经济与贸易、工商管理、计算机科学、商务英语等6个特色专业，现有全日制在校本科生10000余人。","tags":["财经类","本科","民办"],"attrs":{"创建时间":"2001","所在地区":"兰州市城关区店子街45号","院校隶属":"甘肃省教育厅"},"imgs":["https://ss0.bdstatic.com/9bA1vGfa2gU2pMbfm9GUKT-w/timg?wisealaddin&size=f300_300&quality=60&sec=1534504635&di=7ea9a78ea6cad557fa78aa9233968a80&src=http%3A%2F%2Ft10.baidu.com%2Fit%2Fu%3D3749502510%2C954252294%26fm%3D179%26w%3D300%26h%3D300%26img.JPEG","https://ss0.bdstatic.com/9bA1vGfa2gU2pMbfm9GUKT-w/timg?wisealaddin&size=f300_300&quality=60&sec=1534504635&di=9dae6a71650d375e44c941f4b0c296fd&src=http%3A%2F%2Ft11.baidu.com%2Fit%2Fu%3D3643404298%2C774584765%26fm%3D179%26w%3D300%26h%3D300%26img.JPEG","https://ss0.bdstatic.com/9bA1vGfa2gU2pMbfm9GUKT-w/timg?wisealaddin&size=f300_300&quality=60&sec=1534504635&di=7e29deee4910ac02a74fb1ef96f98b17&src=http%3A%2F%2Ft12.baidu.com%2Fit%2Fu%3D3499918292%2C4250149819%26fm%3D179%26app%3D42%26f%3DJPEG%3Fw%3D300%26h%3D300","https://ss0.bdstatic.com/9bA1vGfa2gU2pMbfm9GUKT-w/timg?wisealaddin&size=f300_300&quality=60&sec=1534504635&di=a5d61df4f28ba5146e1bb7ea01f5f333&src=http%3A%2F%2Ft11.baidu.com%2Fit%2Fu%3D3559776967%2C4024973951%26fm%3D179%26w%3D300%26h%3D300%26img.JPEG","https://ss0.bdstatic.com/9bA1vGfa2gU2pMbfm9GUKT-w/timg?wisealaddin&size=f300_300&quality=60&sec=1534504635&di=104306f806e801d70af3c4d6bbf9dc9a&src=http%3A%2F%2Ft11.baidu.com%2Fit%2Fu%3D3660299758%2C884934074%26fm%3D179%26w%3D300%26h%3D300%26img.JPEG","https://ss0.bdstatic.com/9bA1vGfa2gU2pMbfm9GUKT-w/timg?wisealaddin&size=f300_300&quality=60&sec=1534504635&di=e5fd1478f6a12239dc7933fac438f7bf&src=http%3A%2F%2Ft12.baidu.com%2Fit%2Fu%3D3621172259%2C907715297%26fm%3D179%26w%3D300%26h%3D300%26img.JPEG"]}