{"logo":"https://ss0.bdstatic.com/9bA1vGfa2gU2pMbfm9GUKT-w/timg?wisealaddin&size=8&quality=60&sec=1534499416&di=5ff69ee7ec4186cd04c5fd9e9ac3fe52&src=http%3A%2F%2Fh.hiphotos.baidu.com%2Fxiaodu%2Fpic%2Fitem%2F1e30e924b899a9013b79f01a15950a7b0208f54a.jpg","summary":"南京铁道职业技术学院是长三角地区唯一一所轨道交通高职院校，是江苏省教育厅、上海铁路局和浦口区政府三方共建的高职院校，也是轨道交通行业办学历史最长、影响力最大的高职院校之一，被誉为华东地区轨道交通人才培养的“黄埔军校”。是江苏省省级示范性高职院校，为“中俄交通大学联盟”成员高校。学校前身是创建于1941年的南京特别市立第一职业中学，2002年学校升格为高等职业技术学院，更名为南京铁道职业技术学院，2004年成建制由铁道部划转江苏省地方管理。 截至2015年1月，学校占地面积1145亩，总建筑面积29.9万平方米，教学行政用房15.5万平方米，教科研仪器设备总值10119.76万元，图书馆建筑面积达2.36万平方米，馆藏纸质图书58.79万册，多媒体教室112间，计算机2950台。学校5个二级学院和4个教学部，开设29个专业；有专兼职教师556人，全日制在校学生8734人(截至2014年8月31日)。","tags":["理工类","专科","公办"],"attrs":{"创建时间":"1941","所在地区":"江苏省南京市浦口区珍珠南路65号","院校隶属":"江苏省教育厅"},"imgs":["https://ss0.bdstatic.com/9bA1vGfa2gU2pMbfm9GUKT-w/timg?wisealaddin&size=f300_300&quality=60&sec=1534499416&di=8fd62978a2c0fe014ab3489801fb854e&src=http%3A%2F%2Ft10.baidu.com%2Fit%2Fu%3D3517167708%2C3822416672%26fm%3D179%26w%3D300%26h%3D300%26img.JPEG","https://ss0.bdstatic.com/9bA1vGfa2gU2pMbfm9GUKT-w/timg?wisealaddin&size=f300_300&quality=60&sec=1534499416&di=fbb81c232091b854ea44ba96fa070ab7&src=http%3A%2F%2Ft12.baidu.com%2Fit%2Fu%3D2590190498%2C2565687325%26fm%3D179%26w%3D300%26h%3D300%26img.JPEG","https://ss0.bdstatic.com/9bA1vGfa2gU2pMbfm9GUKT-w/timg?wisealaddin&size=f300_300&quality=60&sec=1534499416&di=9bc74b01ab8d45cb61cba0875809cb7d&src=http%3A%2F%2Ft12.baidu.com%2Fit%2Fu%3D3620635379%2C4018601027%26fm%3D179%26w%3D300%26h%3D300%26img.JPEG","https://ss0.bdstatic.com/9bA1vGfa2gU2pMbfm9GUKT-w/timg?wisealaddin&size=f300_300&quality=60&sec=1534499416&di=0f09f05fb86cf7963d4ae0316e910dc2&src=http%3A%2F%2Ft10.baidu.com%2Fit%2Fu%3D3440851080%2C3734618206%26fm%3D179%26w%3D300%26h%3D300%26img.JPEG","https://ss0.bdstatic.com/9bA1vGfa2gU2pMbfm9GUKT-w/timg?wisealaddin&size=f300_300&quality=60&sec=1534499416&di=dcdb4669c0c3393586250eae64e7bfb2&src=http%3A%2F%2Ft10.baidu.com%2Fit%2Fu%3D3499991610%2C4018031742%26fm%3D179%26w%3D300%26h%3D300%26img.JPEG","https://ss0.bdstatic.com/9bA1vGfa2gU2pMbfm9GUKT-w/timg?wisealaddin&size=f300_300&quality=60&sec=1534499416&di=4bfc293a224b89df7e7377e1507c44ef&src=http%3A%2F%2Ft12.baidu.com%2Fit%2Fu%3D3469590038%2C3781842454%26fm%3D179%26w%3D300%26h%3D300%26img.JPEG"]}