{"logo":"https://ss0.bdstatic.com/9bA1vGfa2gU2pMbfm9GUKT-w/timg?wisealaddin&size=8&quality=60&sec=1534504253&di=ae8c130c61bc8e83b0dc118bbfda9e9f&src=http%3A%2F%2Fc.hiphotos.baidu.com%2Fxiaodu%2Fpic%2Fitem%2Fc83d70cf3bc79f3de2c24e1cb2a1cd11728b29fe.jpg","summary":"四川航天职业技术学院是经国家教育部、四川省人民政府批准，面向全国招生的公办全日制普通高等院校，由四川省教育厅、四川省国防科工办、四川航天管理局三方共建；是国家级高技能人才培训基地；是国防科技工业系统在四川的唯一一所高等职业院校。学院的前身四川航天工业学校创办于1965年，2003年经四川省人民政府批准、教育部备案成立四川航天职业技术学院。2011年，经四川省教育厅,四川省财政厅批准，学院成为四川省省级示范性高等职业院校。2017年8月，学院入选为教育部第二批现代学徒制试点单位。2017年11月20日，学院入选四川省优质高等职业院校建设计划立项建设院校。截至2015年12月，学院有龙泉驿校区、广汉三星堆校区一校两区，共占地面积710亩，教学科研仪器设备资产总值6798万元，有校内实践基地63个，校外实习实训基地数156个；设有10个教学系部，开设49个专科专业；有专任教师565人，截至2015年8月，学院在校生总数为12506人。","tags":["理工类","专科","公办"],"attrs":{"创建时间":"1965","所在地区":"成都市龙泉驿区天生路155号","院校隶属":"四川省"},"imgs":["https://ss0.bdstatic.com/9bA1vGfa2gU2pMbfm9GUKT-w/timg?wisealaddin&size=f300_300&quality=60&sec=1534504253&di=2cedcd274d9263c8081781a929d91014&src=http%3A%2F%2Ft12.baidu.com%2Fit%2Fu%3D3631076597%2C831943297%26fm%3D179%26w%3D300%26h%3D300%26img.JPEG","https://ss0.bdstatic.com/9bA1vGfa2gU2pMbfm9GUKT-w/timg?wisealaddin&size=f300_300&quality=60&sec=1534504253&di=b5c4090c95a73f14ea5aedb89d969f74&src=http%3A%2F%2Ft10.baidu.com%2Fit%2Fu%3D3584410230%2C699837968%26fm%3D179%26w%3D300%26h%3D300%26img.JPEG","https://ss0.bdstatic.com/9bA1vGfa2gU2pMbfm9GUKT-w/timg?wisealaddin&size=f300_300&quality=60&sec=1534504253&di=68bd1e8f0d04e7ab3b632ce42f52ab99&src=http%3A%2F%2Ft12.baidu.com%2Fit%2Fu%3D3424830671%2C3761794717%26fm%3D179%26w%3D300%26h%3D300%26img.JPEG","https://ss0.bdstatic.com/9bA1vGfa2gU2pMbfm9GUKT-w/timg?wisealaddin&size=f300_300&quality=60&sec=1534504253&di=791f4c90c0960a54028d7d2e5e0ac104&src=http%3A%2F%2Ft11.baidu.com%2Fit%2Fu%3D3586176745%2C3947613737%26fm%3D179%26w%3D300%26h%3D300%26img.JPEG","https://ss0.bdstatic.com/9bA1vGfa2gU2pMbfm9GUKT-w/timg?wisealaddin&size=f300_300&quality=60&sec=1534504253&di=8018b137ad25f372d23b885e40ac64e6&src=http%3A%2F%2Ft12.baidu.com%2Fit%2Fu%3D1142691830%2C1075762691%26fm%3D179%26app%3D42%26f%3DJPEG%3Fw%3D300%26h%3D300","https://ss0.bdstatic.com/9bA1vGfa2gU2pMbfm9GUKT-w/timg?wisealaddin&size=f300_300&quality=60&sec=1534504253&di=d498b8feafeff3a192b0895b3ae5782f&src=http%3A%2F%2Ft10.baidu.com%2Fit%2Fu%3D3772248261%2C1022882771%26fm%3D179%26w%3D300%26h%3D300%26img.JPEG"]}