{"logo":"https://ss0.bdstatic.com/9bA1vGfa2gU2pMbfm9GUKT-w/timg?wisealaddin&size=8&quality=60&sec=1534423578&di=853f941f56123353e0279fc533493ad8&src=http%3A%2F%2Fd.hiphotos.baidu.com%2Fxiaodu%2Fpic%2Fitem%2F83025aafa40f4bfbb0cc34780b4f78f0f73618f9.jpg","summary":"太原理工大学现代科技学院(简称“太工现代或PITUT”)，位于山西省孝义市，是经国家教育部,山西省人民政府批准成立，由孝义市人民政府和太原理工大学共建，实施本科学历教育的独立学院性质的全日制普通高等学校。学校初期由国家“211工程”重点建设大学——太原理工大学和中国唯一的国家级煤炭行业博物馆——中国煤炭博物馆共同举办。2001年3月，经山西省人民政府同意，太原理工大学现代科技学院开始筹办。2002年5月，经山西省人民政府组织评估后，正式批准太原理工大学现代科技学院成立，以千峰校区为主校区。2014年1月，太原理工大学与孝义市人民政府正式签署合作共建现代科技学院协议。2014年9月17日，学院孝义校区举行启用仪式，宣布正式启用，并作为新的主校区。学校位于吕梁市孝义市胜溪湖湿地公园南畔，截至2017年2月，学校规划总占地面积1500亩，总建筑面积60万平方米。设有17个系(部)，开设工学、文学、法学、经济学、管理学、教育学、艺术学七个学科门类38个本科专业。聘请812名太原理工大学教师负责学院主要教学任务，其中教授、副教授318人，博士、硕士研究生学历的621人。","tags":["理工类","本科","民办"],"attrs":{"创建时间":"2001","所在地区":"山西省太原市新晋祠路45号","院校隶属":"山西省教育厅"},"imgs":["https://ss0.bdstatic.com/9bA1vGfa2gU2pMbfm9GUKT-w/timg?wisealaddin&size=f300_300&quality=60&sec=1534423578&di=c0deb2e6b9a58fea3088ded9f20ee400&src=http%3A%2F%2Ft10.baidu.com%2Fit%2Fu%3D288167970%2C2010166401%26fm%3D179%26app%3D42%26f%3DJPEG%3Fw%3D300%26h%3D300","https://ss0.bdstatic.com/9bA1vGfa2gU2pMbfm9GUKT-w/timg?wisealaddin&size=f300_300&quality=60&sec=1534423578&di=e2f97d478b6564328bd0a4dcaafd150c&src=http%3A%2F%2Ft12.baidu.com%2Fit%2Fu%3D3393227474%2C3817961051%26fm%3D179%26w%3D300%26h%3D300%26img.JPEG","https://ss0.bdstatic.com/9bA1vGfa2gU2pMbfm9GUKT-w/timg?wisealaddin&size=f300_300&quality=60&sec=1534423578&di=e17a92c074154220cd854679f6478811&src=http%3A%2F%2Ft11.baidu.com%2Fit%2Fu%3D3739233436%2C1025168570%26fm%3D179%26w%3D300%26h%3D300%26img.JPEG","https://ss0.bdstatic.com/9bA1vGfa2gU2pMbfm9GUKT-w/timg?wisealaddin&size=f300_300&quality=60&sec=1534423578&di=65ce701387d2a79c4d7b39461b87b99e&src=http%3A%2F%2Ft12.baidu.com%2Fit%2Fu%3D3695572820%2C812328859%26fm%3D179%26w%3D300%26h%3D300%26img.JPEG","https://ss0.bdstatic.com/9bA1vGfa2gU2pMbfm9GUKT-w/timg?wisealaddin&size=f300_300&quality=60&sec=1534423578&di=0f01e8e53957fd9af9975cfd0e66971c&src=http%3A%2F%2Ft11.baidu.com%2Fit%2Fu%3D3395675353%2C3884931547%26fm%3D179%26w%3D300%26h%3D300%26img.JPEG","https://ss0.bdstatic.com/9bA1vGfa2gU2pMbfm9GUKT-w/timg?wisealaddin&size=f300_300&quality=60&sec=1534423578&di=da14b428d3cbd54b291677d7b776abb8&src=http%3A%2F%2Ft10.baidu.com%2Fit%2Fu%3D2760881778%2C2812727145%26fm%3D179%26w%3D300%26h%3D300%26img.JPEG"]}