{"logo":"https://ss0.bdstatic.com/9bA1vGfa2gU2pMbfm9GUKT-w/timg?wisealaddin&size=8&quality=60&sec=1534499601&di=7148376ca1194790cff4ee6b4b43d205&src=http%3A%2F%2Ff.hiphotos.baidu.com%2Fxiaodu%2Fpic%2Fitem%2Fe1fe9925bc315c60c167c0c385b1cb1349547728.jpg","summary":"安徽建筑大学是一所以土建类学科专业为特色的多科性大学，是安徽省与住房和城乡建设部共建高校、教育部本科教学工作水平评估优秀院校、省级博士学位授予权立项建设单位、国家“卓越工程师教育培养计划”实施高校。安徽建筑大学创办于1958年，历经安徽建筑工程学校、安徽建筑工业学院、合肥工业大学建筑分校等办学时期，1986年复办安徽建筑工业学院。2013年安徽建筑工业学院更名为安徽建筑大学。据2018年6月学校官网显示，学校占地面积1531亩，拥有南、北2个校区；设有12个学院，开办61个本科专业；有11个一级学科、46个二级学科硕士学位授权点，5个专业学位授权类别、10个专业学位授权点；共有教职工1300人，全日制本科生近2万人，研究生1000余人。","tags":["理工类","卓越计划","本科","公办"],"attrs":{"创建时间":"1958","所在地区":"合肥市经济技术开发区紫云路292号","院校隶属":"安徽省","硕士点":"57"},"imgs":["https://ss0.bdstatic.com/9bA1vGfa2gU2pMbfm9GUKT-w/timg?wisealaddin&size=f300_300&quality=60&sec=1534499601&di=7e5394db171c20ed5f34dfc0fc0dd7d7&src=http%3A%2F%2Ft12.baidu.com%2Fit%2Fu%3D3536738372%2C3982521700%26fm%3D179%26w%3D300%26h%3D300%26img.JPEG","https://ss0.bdstatic.com/9bA1vGfa2gU2pMbfm9GUKT-w/timg?wisealaddin&size=f300_300&quality=60&sec=1534499601&di=bb05481f5a3acf22838e1eb2b7ec08ba&src=http%3A%2F%2Ft12.baidu.com%2Fit%2Fu%3D3632728793%2C3985888625%26fm%3D179%26w%3D300%26h%3D300%26img.JPEG","https://ss0.bdstatic.com/9bA1vGfa2gU2pMbfm9GUKT-w/timg?wisealaddin&size=f300_300&quality=60&sec=1534499601&di=c9cda44d1fa2420758d20a9376508ea7&src=http%3A%2F%2Ft10.baidu.com%2Fit%2Fu%3D3441609534%2C674007082%26fm%3D179%26w%3D300%26h%3D300%26img.JPEG","https://ss0.bdstatic.com/9bA1vGfa2gU2pMbfm9GUKT-w/timg?wisealaddin&size=f300_300&quality=60&sec=1534499601&di=d038c52dbe2731c51340b0fe1df3b93a&src=http%3A%2F%2Ft10.baidu.com%2Fit%2Fu%3D3616651344%2C4141513928%26fm%3D179%26w%3D300%26h%3D300%26img.JPEG","https://ss0.bdstatic.com/9bA1vGfa2gU2pMbfm9GUKT-w/timg?wisealaddin&size=f300_300&quality=60&sec=1534499601&di=a078ab6f7165fa1b0561c04bd5cc0ffb&src=http%3A%2F%2Ft12.baidu.com%2Fit%2Fu%3D3481727159%2C3832642206%26fm%3D179%26w%3D300%26h%3D300%26img.JPEG","https://ss0.bdstatic.com/9bA1vGfa2gU2pMbfm9GUKT-w/timg?wisealaddin&size=f300_300&quality=60&sec=1534499601&di=6ac38c6206a3ebb57bc9f8779fbc015f&src=http%3A%2F%2Ft12.baidu.com%2Fit%2Fu%3D3612460037%2C662396912%26fm%3D179%26w%3D300%26h%3D300%26img.JPEG"]}