{"logo":"https://ss0.bdstatic.com/9bA1vGfa2gU2pMbfm9GUKT-w/timg?wisealaddin&size=8&quality=60&sec=1534503471&di=f51efeb2231a7b2bdf37c5f051e23de8&src=http%3A%2F%2Fhiphotos.baidu.com%2Fdoc%2Fpic%2Fitem%2F9a504fc2d5628535996de6919aef76c6a6ef63f4.jpg","summary":"广东海洋大学寸金学院(Guangdong Ocean University Cunjin College)是由广东海洋大学与湛江寸金教育集团合作创办一所本科层次的普通全日制公办民助独立学院。学校始建于1999年，时为广东海洋大学的二级学院；2006年经教育部批准其试办独立学院；2010年经省教育厅批准获得专插本招生资格。2012年获得学士学位授予权；2013年通过广东省教育厅独立学院本科教学基本状态评估。海大寸金学院依托广东海洋大学优质的教育资源，由广东海洋大学监控办学质量。广东海洋大学领导、专家、学者担任学院教学指导委员会、教学督导组等机构成员，指导学院学科建设、监督教学质量。截至2016年底，学校校园使用面积1393.2亩，新校区规划建设面积1600多亩。校舍总面积36.73万平方米。教学科研仪器设备总值7359.98万元，图书馆馆藏总量233.8万册(含电子图书90万册)。设有10系2部，开设32个本科专业，有全日制本科在校生20377人。","tags":["理工类","本科","民办"],"attrs":{"创建时间":"1999","所在地区":"广东省湛江市麻章区学智路二号","院校隶属":"广东省教育厅"},"imgs":["https://ss0.bdstatic.com/9bA1vGfa2gU2pMbfm9GUKT-w/timg?wisealaddin&size=f300_300&quality=60&sec=1534503471&di=5a3076dc6b7098e35b3e2da3359f68e7&src=http%3A%2F%2Ft10.baidu.com%2Fit%2Fu%3D3812482308%2C1059749274%26fm%3D179%26w%3D300%26h%3D300%26img.JPEG","https://ss0.bdstatic.com/9bA1vGfa2gU2pMbfm9GUKT-w/timg?wisealaddin&size=f300_300&quality=60&sec=1534503471&di=6d5370e6f3b11e15c1423dd440c85991&src=http%3A%2F%2Ft10.baidu.com%2Fit%2Fu%3D3608659401%2C797306316%26fm%3D179%26w%3D300%26h%3D300%26img.JPEG","https://ss0.bdstatic.com/9bA1vGfa2gU2pMbfm9GUKT-w/timg?wisealaddin&size=f300_300&quality=60&sec=1534503471&di=ca5abae755f5571bb1b2569fc2cfc7db&src=http%3A%2F%2Ft11.baidu.com%2Fit%2Fu%3D3724230868%2C829517324%26fm%3D179%26w%3D300%26h%3D300%26img.JPEG","https://ss0.bdstatic.com/9bA1vGfa2gU2pMbfm9GUKT-w/timg?wisealaddin&size=f300_300&quality=60&sec=1534503471&di=d317a480005c4405377aa27bd85b2d82&src=http%3A%2F%2Ft11.baidu.com%2Fit%2Fu%3D3688092400%2C812280775%26fm%3D179%26w%3D300%26h%3D300%26img.JPEG","https://ss0.bdstatic.com/9bA1vGfa2gU2pMbfm9GUKT-w/timg?wisealaddin&size=f300_300&quality=60&sec=1534503471&di=c1b32e3e0c7eb1608b0502e09489a296&src=http%3A%2F%2Ft11.baidu.com%2Fit%2Fu%3D3717519286%2C887128469%26fm%3D179%26w%3D300%26h%3D300%26img.JPEG","https://ss0.bdstatic.com/9bA1vGfa2gU2pMbfm9GUKT-w/timg?wisealaddin&size=f300_300&quality=60&sec=1534503471&di=9d382956b4f5aaa8eb58162cf46357b7&src=http%3A%2F%2Ft12.baidu.com%2Fit%2Fu%3D3614240450%2C4137015521%26fm%3D179%26w%3D300%26h%3D300%26img.JPEG"]}