{"logo":"https://ss0.bdstatic.com/9bA1vGfa2gU2pMbfm9GUKT-w/timg?wisealaddin&size=8&quality=60&sec=1534504545&di=8d5bf5903e49c099500ed1b3822d55c7&src=http%3A%2F%2Fc.hiphotos.baidu.com%2Fxiaodu%2Fpic%2Fitem%2Fe850352ac65c1038e96c64eeba119313b07e8988.jpg","summary":"榆林学院(Yulin University)坐落在陕西榆林，是一所以工科为主，工、管、文、理、农、法等多学科协调发展的省属本科院校，是陕西省最北部的高等院校，也是榆林唯一的一所省属本科院校。入选卓越农林人才教育培养计划。学校前身是创建于1923年的陕西省立第四师范学校，1958年改名为西安师范学院绥德分院，1978年更名为陕西师范大学榆林专修科，80年代初期北迁至榆林西沙，1984年更名为榆林师范专科学校，1991年与榆林农林专科学校合并，整合为榆林高等专科学校，2003年经教育部批准升格为本科院校，定名为榆林学院。2015年1月，陕西省教育厅,榆林市人民政府签订了省市共建协议，合力推进榆林大学建设。2017年，绥德师范学校并入。2018年，学校被教育部确定为新增硕士学位授权单位，被陕西省确定为一流应用型本科院校建设单位。据2018年5月学校官网信息显示，学校占地517亩，设有15个院系部、53个本科专业；有教职员工970多人，全日制在校学生12500多人。","tags":["综合类","本科","公办"],"attrs":{"创建时间":"1958","所在地区":"榆林市崇文西路4号","院校隶属":"陕西省"},"imgs":["https://ss0.bdstatic.com/9bA1vGfa2gU2pMbfm9GUKT-w/timg?wisealaddin&size=f300_300&quality=60&sec=1534504545&di=77f6020b59673d943aa79266c8109a09&src=http%3A%2F%2Ft10.baidu.com%2Fit%2Fu%3D3550956696%2C713143066%26fm%3D179%26w%3D300%26h%3D300%26img.JPEG","https://ss0.bdstatic.com/9bA1vGfa2gU2pMbfm9GUKT-w/timg?wisealaddin&size=f300_300&quality=60&sec=1534504545&di=d9a5080aa304119a25b199bdf5974ea2&src=http%3A%2F%2Ft11.baidu.com%2Fit%2Fu%3D3754956043%2C1008237762%26fm%3D179%26w%3D300%26h%3D300%26img.JPEG","https://ss0.bdstatic.com/9bA1vGfa2gU2pMbfm9GUKT-w/timg?wisealaddin&size=f300_300&quality=60&sec=1534504545&di=995cca025d12fbc2d91d505d068b09e5&src=http%3A%2F%2Ft12.baidu.com%2Fit%2Fu%3D2868510377%2C2944258297%26fm%3D179%26w%3D300%26h%3D300%26img.JPEG","https://ss0.bdstatic.com/9bA1vGfa2gU2pMbfm9GUKT-w/timg?wisealaddin&size=f300_300&quality=60&sec=1534504545&di=417db958446b95b62f27bb2e33263881&src=http%3A%2F%2Ft10.baidu.com%2Fit%2Fu%3D3641704803%2C3988203353%26fm%3D179%26w%3D300%26h%3D300%26img.JPEG","https://ss0.bdstatic.com/9bA1vGfa2gU2pMbfm9GUKT-w/timg?wisealaddin&size=f300_300&quality=60&sec=1534504545&di=015046447b2bedcbbef22e78f9f98387&src=http%3A%2F%2Ft10.baidu.com%2Fit%2Fu%3D2660372964%2C2637926088%26fm%3D179%26w%3D300%26h%3D300%26img.JPEG","https://ss0.bdstatic.com/9bA1vGfa2gU2pMbfm9GUKT-w/timg?wisealaddin&size=f300_300&quality=60&sec=1534504545&di=254655e1dbabdab0935ba6b3029a5d39&src=http%3A%2F%2Ft11.baidu.com%2Fit%2Fu%3D3541903348%2C742068384%26fm%3D179%26w%3D300%26h%3D300%26img.JPEG"]}