{"logo":"https://ss0.bdstatic.com/9bA1vGfa2gU2pMbfm9GUKT-w/timg?wisealaddin&size=8&quality=60&sec=1534502844&di=15c742bc7894005ccf4132e20837fa3c&src=http%3A%2F%2Fc.hiphotos.baidu.com%2Fxiaodu%2Fpic%2Fitem%2Fdbb44aed2e738bd4d98b181da98b87d6277ff970.jpg","summary":"武汉科技大学(Wuhan University of Science and Technology)是中华人民共和国教育部、湖北省人民政府、宝钢集团有限公司、鞍山钢铁集团公司、武汉钢铁(集团)公司、首钢集团、中国冶金科工集团有限公司、中国中钢集团公司共同参与建设的省部共建大学，是国家\"中西部高校基础能力建设工程\"100所重点建设大学之一，入选湖北省“双一流”建设高校，是国家卓越工程师教育培养计划实施高校，是教育部本科教育评估优秀高校，湖北省省属重点综合性大学，拥有湖北省属高校第一个国家重点实验室，第一个国家工程研究中心。 武汉科技大学办学历史溯源于1898年清末湖广总督张之洞奏请清朝政府批准成立的湖北工艺学堂，历经湖北中等工业学堂、湖北甲种工业学校、汉阳高级工业职业学校、武昌高级工业学校、中南钢铁工业学校、武昌钢铁工业学校的传承与发展，1958年组建为武汉钢铁学院，开办本科教育。1995年，隶属于原冶金部的武汉钢铁学院、武汉建筑高等专科学校、武汉冶金医学高等专科学校合并组建为武汉冶金科技大学。1999年更为现名。截至2015年6月，学校图书馆藏书刊221余万册。教学科研仪器设备总值超过2亿元；建有32个研究所、1所三级甲等直属附属医院、4所非直属附属医院。截至2016年4月，学校校园总面积170.93万平方米，校舍建筑面积104.15万平方米。各类全日制在校学生3万余人。","tags":["理工类","卓越计划","国防生","本科"],"attrs":{"创建时间":"1898","所在地区":"青山校区位于武汉市青山区和平大道947","院校隶属":"湖北省","重点学科数":"1","院士数":"6","博士点":"8","硕士点":"179"},"imgs":["https://ss0.bdstatic.com/9bA1vGfa2gU2pMbfm9GUKT-w/timg?wisealaddin&size=f300_300&quality=60&sec=1534502844&di=a082b88d4b8d5df2a5df5b04acbecbee&src=http%3A%2F%2Ft11.baidu.com%2Fit%2Fu%3D3625678723%2C4202878814%26fm%3D179%26w%3D300%26h%3D300%26img.JPEG","https://ss0.bdstatic.com/9bA1vGfa2gU2pMbfm9GUKT-w/timg?wisealaddin&size=f300_300&quality=60&sec=1534502844&di=720d7fa22eca88e73e053e16aa56b5ea&src=http%3A%2F%2Ft11.baidu.com%2Fit%2Fu%3D3665664493%2C814160548%26fm%3D179%26w%3D300%26h%3D300%26img.JPEG","https://ss0.bdstatic.com/9bA1vGfa2gU2pMbfm9GUKT-w/timg?wisealaddin&size=f300_300&quality=60&sec=1534502844&di=a3f0dd678c6041f93364f48d0c5ae455&src=http%3A%2F%2Ft12.baidu.com%2Fit%2Fu%3D3711338675%2C969061407%26fm%3D179%26w%3D300%26h%3D300%26img.JPEG","https://ss0.bdstatic.com/9bA1vGfa2gU2pMbfm9GUKT-w/timg?wisealaddin&size=f300_300&quality=60&sec=1534502844&di=4f899b11518f6231bbaa57e8e6fa86ab&src=http%3A%2F%2Ft11.baidu.com%2Fit%2Fu%3D2662271611%2C2410801801%26fm%3D179%26w%3D300%26h%3D300%26img.JPEG","https://ss0.bdstatic.com/9bA1vGfa2gU2pMbfm9GUKT-w/timg?wisealaddin&size=f300_300&quality=60&sec=1534502844&di=5ba3dbb36fa2d9714b67123928cae14e&src=http%3A%2F%2Ft10.baidu.com%2Fit%2Fu%3D3405346392%2C3908283320%26fm%3D179%26w%3D300%26h%3D300%26img.JPEG","https://ss0.bdstatic.com/9bA1vGfa2gU2pMbfm9GUKT-w/timg?wisealaddin&size=f300_300&quality=60&sec=1534502844&di=e4fed9ee1c6a8e4e7191d8b0b892b502&src=http%3A%2F%2Ft12.baidu.com%2Fit%2Fu%3D724387343%2C532343273%26fm%3D179%26app%3D42%26f%3DJPEG%3Fw%3D300%26h%3D300"]}