{"logo":"https://ss0.bdstatic.com/9bA1vGfa2gU2pMbfm9GUKT-w/timg?wisealaddin&size=8&quality=60&sec=1534502444&di=77f69f63571f2a17ef861d5e8ac849db&src=http%3A%2F%2Fg.hiphotos.baidu.com%2Fxiaodu%2Fpic%2Fitem%2Fd52a2834349b033bf52c56f61dce36d3d539bd72.jpg","summary":"江西工业贸易职业技术学院是国家教育部批准成立的一所集文、理、经、工、管、艺术和体育等学科门类齐全的综合性、现代化、公办省级示范性高等职业院校，2015年经江西省教育厅批准为“江西省应用技术型本科试点院校”，招收本科土木工程专业学生。2016年获评“江西省优质专科高等职业院校建设计划立项单位”。2016年8月，入选第二批国家现代学徒制试点单位。学院创建于1964年，占地540亩，可容纳全日制在校生10000余人。学院位于风景秀丽，大学荟萃的南昌市红角洲高校园区，毗邻南昌大学、南昌航空大学、南昌陆军学院、江西科技师范大学、江西中医药大学、江西警察学院、江西经济管理干部学院等省内知名高等学府。是全国德育工作先进院校、江西省普通高校毕业生就业工作先进院校、江西省首批高技能人才培养示范院校。建校五十多年来，学院为国家培养了三万多名高中级管理和技术人才，涌现出一大批享誉省内外的企业家和政界、经济界、金融界高级管理人才，为国家经济发展和社会进步做出了重要贡献。","tags":["综合类","专科","公办"],"attrs":{"创建时间":"1964","所在地区":"江西省南昌市红角洲高校园区嘉言路699号","院校隶属":"江西省"},"imgs":["https://ss0.bdstatic.com/9bA1vGfa2gU2pMbfm9GUKT-w/timg?wisealaddin&size=f300_300&quality=60&sec=1534502444&di=f87f33e5113fac5bc22c35638593f10e&src=http%3A%2F%2Ft10.baidu.com%2Fit%2Fu%3D3596025633%2C857406686%26fm%3D179%26w%3D300%26h%3D300%26img.JPEG","https://ss0.bdstatic.com/9bA1vGfa2gU2pMbfm9GUKT-w/timg?wisealaddin&size=f300_300&quality=60&sec=1534502444&di=d3423291cffee03a0e545d302b93e6ad&src=http%3A%2F%2Ft12.baidu.com%2Fit%2Fu%3D3577641116%2C837545494%26fm%3D179%26w%3D300%26h%3D300%26img.JPEG","https://ss0.bdstatic.com/9bA1vGfa2gU2pMbfm9GUKT-w/timg?wisealaddin&size=f300_300&quality=60&sec=1534502444&di=1a5e33ce873eef165d49e86cde9bda15&src=http%3A%2F%2Ft10.baidu.com%2Fit%2Fu%3D3677953956%2C834087077%26fm%3D179%26w%3D300%26h%3D300%26img.JPEG","https://ss0.bdstatic.com/9bA1vGfa2gU2pMbfm9GUKT-w/timg?wisealaddin&size=f300_300&quality=60&sec=1534502444&di=2eaaf00dc1db46220c3f9d1229018252&src=http%3A%2F%2Ft12.baidu.com%2Fit%2Fu%3D3596539781%2C875533556%26fm%3D179%26w%3D300%26h%3D300%26img.JPEG","https://ss0.bdstatic.com/9bA1vGfa2gU2pMbfm9GUKT-w/timg?wisealaddin&size=f300_300&quality=60&sec=1534502444&di=09af695ec21d4b91ea20a3eb185f02c0&src=http%3A%2F%2Ft12.baidu.com%2Fit%2Fu%3D3602411405%2C666623369%26fm%3D179%26w%3D300%26h%3D300%26img.JPEG","https://ss0.bdstatic.com/9bA1vGfa2gU2pMbfm9GUKT-w/timg?wisealaddin&size=f300_300&quality=60&sec=1534502444&di=d2e3155b45b91670dfe8e69b27ccb8f0&src=http%3A%2F%2Ft12.baidu.com%2Fit%2Fu%3D3684015176%2C721491410%26fm%3D179%26w%3D300%26h%3D300%26img.JPEG"]}