{"logo":"https://ss0.bdstatic.com/9bA1vGfa2gU2pMbfm9GUKT-w/timg?wisealaddin&size=8&quality=60&sec=1534499570&di=8fe56a2dcd83149960b68a969b6990ac&src=http%3A%2F%2Fa.hiphotos.baidu.com%2Fxiaodu%2Fpic%2Fitem%2F0bd162d9f2d3572c915536f08213632762d0c363.jpg","summary":"浙江农林大学暨阳学院(原浙江农林大学天目学院)，位于绍兴，创办于2000年，由浙江林学院(浙江农林大学前身)申请，经浙江省人民政府批准设立的全日制本科独立学院。2004年经教育部重新确认，2011年与诸暨市人民政府合作共建、与诸暨市教育发展投资有限公司合作举办。2013年9月，学院整体从浙江省临安市迁址到浙江省诸暨市办学。2014年9月28日上午，浙江农林大学天目学院举行更名揭牌仪式，正式更名为浙江农林大学暨阳学院。","tags":["农林类","本科","民办"],"attrs":{"创建时间":"2000","所在地区":"浙江省诸暨市浦阳路77号","院校隶属":"浙江省教育厅"},"imgs":["https://ss0.bdstatic.com/9bA1vGfa2gU2pMbfm9GUKT-w/timg?wisealaddin&size=f300_300&quality=60&sec=1534499570&di=6a27f99fce87f2acfbf162701612301e&src=http%3A%2F%2Ft10.baidu.com%2Fit%2Fu%3D3633448512%2C880940585%26fm%3D179%26w%3D300%26h%3D300%26img.JPEG","https://ss0.bdstatic.com/9bA1vGfa2gU2pMbfm9GUKT-w/timg?wisealaddin&size=f300_300&quality=60&sec=1534499570&di=ae1fe5e701e649f4685ff8738649725e&src=http%3A%2F%2Ft10.baidu.com%2Fit%2Fu%3D3770328699%2C894338361%26fm%3D179%26w%3D300%26h%3D300%26img.JPEG","https://ss0.bdstatic.com/9bA1vGfa2gU2pMbfm9GUKT-w/timg?wisealaddin&size=f300_300&quality=60&sec=1534499570&di=3f430d168278789b1a517fce5aaaa57b&src=http%3A%2F%2Ft11.baidu.com%2Fit%2Fu%3D3622034065%2C735286051%26fm%3D179%26w%3D300%26h%3D300%26img.JPEG","https://ss0.bdstatic.com/9bA1vGfa2gU2pMbfm9GUKT-w/timg?wisealaddin&size=f300_300&quality=60&sec=1534499570&di=9f0e0035ee3c7d1f0f220270b712291c&src=http%3A%2F%2Ft10.baidu.com%2Fit%2Fu%3D3681453114%2C916755547%26fm%3D179%26w%3D300%26h%3D300%26img.JPEG","https://ss0.bdstatic.com/9bA1vGfa2gU2pMbfm9GUKT-w/timg?wisealaddin&size=f300_300&quality=60&sec=1534499570&di=538f202b50dff0bf37d65fefac75b6f8&src=http%3A%2F%2Ft12.baidu.com%2Fit%2Fu%3D3738768902%2C965674451%26fm%3D179%26w%3D300%26h%3D300%26img.JPEG","https://ss0.bdstatic.com/9bA1vGfa2gU2pMbfm9GUKT-w/timg?wisealaddin&size=f300_300&quality=60&sec=1534499570&di=30eddba354b2ed2b8fb158efd32edcf0&src=http%3A%2F%2Ft10.baidu.com%2Fit%2Fu%3D3691380528%2C918985158%26fm%3D179%26w%3D300%26h%3D300%26img.JPEG"]}