{"logo":"https://ss0.bdstatic.com/9bA1vGfa2gU2pMbfm9GUKT-w/timg?wisealaddin&size=8&quality=60&sec=1534502201&di=2c9fe858a8146f73a1cd87940642d262&src=http%3A%2F%2Ff.hiphotos.baidu.com%2Fxiaodu%2Fpic%2Fitem%2F0b7b02087bf40ad11f3d6dcf5f2c11dfa8eccec5.jpg","summary":"漳州职业技术学院是由福建漳州市人民政府举办的一所全日制公办普通高职院校，是国家示范性高等职业院校、全国毕业生就业典型经验高校、全国职业教育先进单位。学校前身为创办于1984年的漳州职业大学，2002年4月更名为漳州职业技术学院，2004年成功通过高职高专人才培养工作水平优秀评估。截至2013年年末，该校共有用地1250亩，教学仪器设备总值1.11亿元，图书资料88万册；设有10系2部(2015年数据)，68个专科专业；有专任教师648人，在校生13880人。","tags":["理工类","专科","公办"],"attrs":{"创建时间":"1984","所在地区":"福建省漳州市马鞍山路1号","院校隶属":"福建省"},"imgs":["https://ss0.bdstatic.com/9bA1vGfa2gU2pMbfm9GUKT-w/timg?wisealaddin&size=f300_300&quality=60&sec=1534502202&di=c3b73fc9caf6e23df6afa12b9456262c&src=http%3A%2F%2Ft11.baidu.com%2Fit%2Fu%3D3686050015%2C834264656%26fm%3D179%26w%3D300%26h%3D300%26img.JPEG","https://ss0.bdstatic.com/9bA1vGfa2gU2pMbfm9GUKT-w/timg?wisealaddin&size=f300_300&quality=60&sec=1534502202&di=0612d59ce02bc7d5c4eaa262cb0d32ea&src=http%3A%2F%2Ft11.baidu.com%2Fit%2Fu%3D2824165264%2C2754428589%26fm%3D179%26w%3D300%26h%3D300%26img.JPEG","https://ss0.bdstatic.com/9bA1vGfa2gU2pMbfm9GUKT-w/timg?wisealaddin&size=f300_300&quality=60&sec=1534502202&di=65d6eadc65d87d67da5fbb079bbec1d2&src=http%3A%2F%2Ft10.baidu.com%2Fit%2Fu%3D3725390763%2C772992205%26fm%3D179%26w%3D300%26h%3D300%26img.JPEG","https://ss0.bdstatic.com/9bA1vGfa2gU2pMbfm9GUKT-w/timg?wisealaddin&size=f300_300&quality=60&sec=1534502202&di=c506cb49ea7d1be8e50913eff22286c3&src=http%3A%2F%2Ft12.baidu.com%2Fit%2Fu%3D3775705055%2C1024073693%26fm%3D179%26w%3D300%26h%3D300%26img.JPEG","https://ss0.bdstatic.com/9bA1vGfa2gU2pMbfm9GUKT-w/timg?wisealaddin&size=f300_300&quality=60&sec=1534502202&di=cd5cfdc22fa73562e187dbcccd8ddc2d&src=http%3A%2F%2Ft11.baidu.com%2Fit%2Fu%3D3387591637%2C3656873783%26fm%3D179%26w%3D300%26h%3D300%26img.JPEG","https://ss0.bdstatic.com/9bA1vGfa2gU2pMbfm9GUKT-w/timg?wisealaddin&size=f300_300&quality=60&sec=1534502202&di=ad8cbdb0d669a3dbe1f141c98a2f1f84&src=http%3A%2F%2Ft10.baidu.com%2Fit%2Fu%3D3338747058%2C3691696248%26fm%3D179%26w%3D300%26h%3D300%26img.JPEG"]}