{"logo":"https://ss0.bdstatic.com/9bA1vGfa2gU2pMbfm9GUKT-w/timg?wisealaddin&size=8&quality=60&sec=1534499416&di=7518dc64ceee5b0aa2d0dc406499492b&src=http%3A%2F%2Fd.hiphotos.baidu.com%2Fxiaodu%2Fpic%2Fitem%2F060828381f30e924cbae091d44086e061d95f790.jpg","summary":"盐城师范学院，是江苏省属高等师范本科院校，坐落在江苏沿海开放城市盐城市。学校创建于1958年，前身是盐城师范专科学校和盐城教育学院；2002年国家级重点中专盐城商业学校并入；2013年该校入选新疆维吾尔自治区“国培计划”项目——农村小学语文教师脱产置换培训项目。截至2016年5月，学校有通榆和新长两个校区，校园占地面积近1500亩，校舍建筑面积58万平方米；现有70个本科专业，其中师范类18个，非师范类52个；在校生36000余人，其中全日制本科在校生21000余人，成人学历教育学员15000人。","tags":["师范类","本科","公办"],"attrs":{"创建时间":"1999","所在地区":"江苏省盐城市开放大道50号","院校隶属":"江苏省人民政府","硕士点":"14"},"imgs":["https://ss0.bdstatic.com/9bA1vGfa2gU2pMbfm9GUKT-w/timg?wisealaddin&size=f300_300&quality=60&sec=1534499416&di=465e43852e3cecbe87e27beaaec157f6&src=http%3A%2F%2Ft10.baidu.com%2Fit%2Fu%3D3664653792%2C857541023%26fm%3D179%26w%3D300%26h%3D300%26img.JPEG","https://ss0.bdstatic.com/9bA1vGfa2gU2pMbfm9GUKT-w/timg?wisealaddin&size=f300_300&quality=60&sec=1534499416&di=4582753f2528dd190224dcd034bce0e6&src=http%3A%2F%2Ft11.baidu.com%2Fit%2Fu%3D3670456150%2C929542436%26fm%3D179%26w%3D300%26h%3D300%26img.JPEG","https://ss0.bdstatic.com/9bA1vGfa2gU2pMbfm9GUKT-w/timg?wisealaddin&size=f300_300&quality=60&sec=1534499416&di=1ebe259f4d005ca90d48d75e0559364e&src=http%3A%2F%2Ft12.baidu.com%2Fit%2Fu%3D3636170666%2C4160886369%26fm%3D179%26w%3D300%26h%3D300%26img.JPEG","https://ss0.bdstatic.com/9bA1vGfa2gU2pMbfm9GUKT-w/timg?wisealaddin&size=f300_300&quality=60&sec=1534499416&di=3e23f450107120790ed00951233a8286&src=http%3A%2F%2Ft10.baidu.com%2Fit%2Fu%3D2849215953%2C2662927274%26fm%3D179%26w%3D300%26h%3D300%26img.JPEG","https://ss0.bdstatic.com/9bA1vGfa2gU2pMbfm9GUKT-w/timg?wisealaddin&size=f300_300&quality=60&sec=1534499416&di=bca4c735e0e04ed6d81c8245c51c37f7&src=http%3A%2F%2Ft10.baidu.com%2Fit%2Fu%3D2786641566%2C2933041482%26fm%3D179%26w%3D300%26h%3D300%26img.JPEG","https://ss0.bdstatic.com/9bA1vGfa2gU2pMbfm9GUKT-w/timg?wisealaddin&size=f300_300&quality=60&sec=1534499416&di=d7fcd16a3f290656d1354df6f13eee17&src=http%3A%2F%2Ft10.baidu.com%2Fit%2Fu%3D3478239105%2C3789261173%26fm%3D179%26w%3D300%26h%3D300%26img.JPEG"]}