{"logo":"https://ss0.bdstatic.com/9bA1vGfa2gU2pMbfm9GUKT-w/timg?wisealaddin&size=8&quality=60&sec=1534504211&di=9ec3f7e3a89fd7dcb9e133483e6a8131&src=http%3A%2F%2Fe.hiphotos.baidu.com%2Fxiaodu%2Fpic%2Fitem%2Fd6ca7bcb0a46f21f2248cb7ffe246b600c33ae9a.jpg","summary":"重庆工商职业学院，位于重庆市，是由重庆市人民政府举办，经教育部批准设立的公办全日制普通高等学校，面向全国招生。学院是国家骨干高职院校建设单位、第二批国家现代学徒制试点单位、重庆市示范性高等职业学院、重庆市普通高校毕业生就业工作先进集体、重庆市学生管理工作先进集体、重庆市安全文明校园。重庆工商职业学院现有九龙坡华岩和合川两个校区，占地总面积1339亩，现有建筑面积28.8万平方米。","tags":["综合类","专科","公办"],"attrs":{"创建时间":"2005","所在地区":"九龙坡区九龙科技园华龙大道1号楼102","院校隶属":"重庆市教育委员会"},"imgs":["https://ss0.bdstatic.com/9bA1vGfa2gU2pMbfm9GUKT-w/timg?wisealaddin&size=f300_300&quality=60&sec=1534504211&di=8f24fd8cd53d7b3178be378198de6fa4&src=http%3A%2F%2Ft12.baidu.com%2Fit%2Fu%3D3576965819%2C732290816%26fm%3D179%26w%3D300%26h%3D300%26img.JPEG","https://ss0.bdstatic.com/9bA1vGfa2gU2pMbfm9GUKT-w/timg?wisealaddin&size=f300_300&quality=60&sec=1534504211&di=f49f67a4da0717155af1611f46f75a2c&src=http%3A%2F%2Ft10.baidu.com%2Fit%2Fu%3D3685566783%2C819167790%26fm%3D179%26w%3D300%26h%3D300%26img.JPEG","https://ss0.bdstatic.com/9bA1vGfa2gU2pMbfm9GUKT-w/timg?wisealaddin&size=f300_300&quality=60&sec=1534504211&di=2ee4ca9c4ddcd998dbb5668616810725&src=http%3A%2F%2Ft10.baidu.com%2Fit%2Fu%3D3509564751%2C3990143421%26fm%3D179%26w%3D300%26h%3D300%26img.JPEG","https://ss0.bdstatic.com/9bA1vGfa2gU2pMbfm9GUKT-w/timg?wisealaddin&size=f300_300&quality=60&sec=1534504211&di=0ec53186ee12d393779cd84e9bffabe6&src=http%3A%2F%2Ft12.baidu.com%2Fit%2Fu%3D3396314591%2C3887440678%26fm%3D179%26w%3D300%26h%3D300%26img.JPEG","https://ss0.bdstatic.com/9bA1vGfa2gU2pMbfm9GUKT-w/timg?wisealaddin&size=f300_300&quality=60&sec=1534504211&di=72f6af261242b0704b7a0c91827fadc3&src=http%3A%2F%2Ft12.baidu.com%2Fit%2Fu%3D3741449144%2C1037158406%26fm%3D179%26w%3D300%26h%3D300%26img.JPEG","https://ss0.bdstatic.com/9bA1vGfa2gU2pMbfm9GUKT-w/timg?wisealaddin&size=f300_300&quality=60&sec=1534504211&di=0fe2d380446edf43eb203b53994a0909&src=http%3A%2F%2Ft11.baidu.com%2Fit%2Fu%3D3697184167%2C752974002%26fm%3D179%26w%3D300%26h%3D300%26img.JPEG"]}