{"logo":"https://ss0.bdstatic.com/9bA1vGfa2gU2pMbfm9GUKT-w/timg?wisealaddin&size=8&quality=60&sec=1534493849&di=f6ac68a623fd7501ed0d1957a9a0ca9b&src=http%3A%2F%2Ff.hiphotos.baidu.com%2Fxiaodu%2Fpic%2Fitem%2F38dbb6fd5266d0163c150b049f2bd40735fa3589.jpg","summary":"黑龙江生物科技职业学院坐落在北国冰城-哈尔滨市松花江北岸大学城内，是一所公办普通高等职业院校，隶属于黑龙江省农业委员会，省级文明单位标兵。学院是黑龙江省唯一一所集生物工程、水产养殖、畜牧兽医、农业种植等多学科多领域的高等职业院校。2016年8月，入选第二批国家现代学徒制试点单位。截至2017年9月，学院总占地面积69.82万平方米，建筑面积20.44万平方米，馆藏纸质图书45.96万册，有1个中央财政支持的职教实训基地，181个校内实验实训室和259个校外实训基地，多媒体教学设备覆盖全部教室。学院设有8个系和3部，开设39个高职专业；有专任教师333人，目前在校生8000余人。","tags":["综合类","专科","公办"],"attrs":{"创建时间":"1948","所在地区":"哈尔滨市利民开发区学院路群英街","院校隶属":"黑龙江省教育厅"},"imgs":["https://ss0.bdstatic.com/9bA1vGfa2gU2pMbfm9GUKT-w/timg?wisealaddin&size=f300_300&quality=60&sec=1534493849&di=ec15391eb564e5fccdc40af0aa95d5e4&src=http%3A%2F%2Ft10.baidu.com%2Fit%2Fu%3D3495914274%2C3999598845%26fm%3D179%26w%3D300%26h%3D300%26img.JPEG","https://ss0.bdstatic.com/9bA1vGfa2gU2pMbfm9GUKT-w/timg?wisealaddin&size=f300_300&quality=60&sec=1534493849&di=9f1ecf2c9a28fd57cbf644f8dce98f8e&src=http%3A%2F%2Ft10.baidu.com%2Fit%2Fu%3D3677272461%2C745035137%26fm%3D179%26w%3D300%26h%3D300%26img.JPEG","https://ss0.bdstatic.com/9bA1vGfa2gU2pMbfm9GUKT-w/timg?wisealaddin&size=f300_300&quality=60&sec=1534493849&di=6bebe2f947b127baba0e1444f2b6a91c&src=http%3A%2F%2Ft10.baidu.com%2Fit%2Fu%3D3650308881%2C708056597%26fm%3D179%26w%3D300%26h%3D300%26img.JPEG","https://ss0.bdstatic.com/9bA1vGfa2gU2pMbfm9GUKT-w/timg?wisealaddin&size=f300_300&quality=60&sec=1534493849&di=4ebce18b57977558282b4cb41198b091&src=http%3A%2F%2Ft11.baidu.com%2Fit%2Fu%3D3639662191%2C774051371%26fm%3D179%26w%3D300%26h%3D300%26img.JPEG","https://ss0.bdstatic.com/9bA1vGfa2gU2pMbfm9GUKT-w/timg?wisealaddin&size=f300_300&quality=60&sec=1534493849&di=6f097ae7767dbe1c244208791bf1d2fe&src=http%3A%2F%2Ft11.baidu.com%2Fit%2Fu%3D2517192694%2C3139067169%26fm%3D179%26app%3D42%26f%3DJPEG%3Fw%3D300%26h%3D300","https://ss0.bdstatic.com/9bA1vGfa2gU2pMbfm9GUKT-w/timg?wisealaddin&size=f300_300&quality=60&sec=1534493849&di=91a96bbd4c416347ae1e11be23a45f09&src=http%3A%2F%2Ft11.baidu.com%2Fit%2Fu%3D3779652259%2C880577216%26fm%3D179%26w%3D300%26h%3D300%26img.JPEG"]}